precompiled-0.1.11.dist-info/METADATA
precompiled-0.1.11.dist-info/WHEEL
precompiled-0.1.11.dist-info/entry_points.txt
precompiled/__init__.py
precompiled/all.py
precompiled/listnode.py
precompiled/nestedinteger.py
precompiled/node.py
precompiled/testcase.py
precompiled/treenode.py
precompiled/treenode_base.py
precompiled-0.1.11.dist-info/RECORD
