Metadata-Version: 2.1
Name: precompiled
Version: 0.1.11
Summary: leetcode precompiled package
Author-Email: zonewave <ybzhang17@163.com>
License: MIT
Project-URL: Homepage, https://github.com/zonewave/leetcode-precompiled/tree/master/py
Project-URL: Issues, https://github.com/zonewave/leetcode-precompiled/issues
Requires-Python: >=3.7
Requires-Dist: flake8>=5.0.4
Requires-Dist: coverage>=7.2.7
